jmse/__init__.py
jmse-0.0.0.dist-info/METADATA
jmse-0.0.0.dist-info/RECORD
jmse-0.0.0.dist-info/WHEEL
jmse-0.0.0.dist-info/top_level.txt
